{
  "id": "api/hooks/index",
  "title": "hooks",
  "description": "Functions",
  "source": "@site/docs/api/hooks/index.md",
  "sourceDirName": "api/hooks",
  "slug": "/api/hooks/",
  "permalink": "/docs/api/hooks/",
  "draft": false,
  "unlisted": false,
  "editUrl": "https://github.com/facebook/docusaurus/tree/main/packages/create-docusaurus/templates/shared/docs/api/hooks/index.md",
  "tags": [],
  "version": "current",
  "frontMatter": {},
  "sidebar": "tutorialSidebar",
  "previous": {
    "title": "TestComp()",
    "permalink": "/docs/api/components/functions/TestComp"
  },
  "next": {
    "title": "useMount()",
    "permalink": "/docs/api/hooks/functions/useMount"
  }
}